neurodev_mcp/__init__.py
neurodev_mcp/server.py
neurodev_mcp/analyzers/__init__.py
neurodev_mcp/analyzers/code_analyzer.py
neurodev_mcp/executors/__init__.py
neurodev_mcp/executors/test_executor.py
neurodev_mcp/generators/__init__.py
neurodev_mcp/generators/test_generator.py
neurodev_mcp-0.2.0.dist-info/licenses/LICENSE
neurodev_mcp-0.2.0.dist-info/METADATA
neurodev_mcp-0.2.0.dist-info/WHEEL
neurodev_mcp-0.2.0.dist-info/entry_points.txt
neurodev_mcp-0.2.0.dist-info/top_level.txt
neurodev_mcp-0.2.0.dist-info/RECORD
