Metadata-Version: 2.4
Name: neurodev-mcp
Version: 0.2.0
Summary: Smart MCP server for code review, test generation, and code execution with SSE and HTTP streaming support
Author-email: NeuroDev Team <team@neurodev.io>
License-Expression: MIT
Project-URL: Homepage, https://github.com/ravikant1918/neurodev-mcp
Project-URL: Documentation, https://github.com/ravikant1918/neurodev-mcp#readme
Project-URL: Repository, https://github.com/ravikant1918/neurodev-mcp
Project-URL: Issues, https://github.com/ravikant1918/neurodev-mcp/issues
Keywords: mcp,model-context-protocol,code-review,test-generation,static-analysis,pytest,python-development
Classifier: Development Status :: 3 - Alpha
Classifier: Intended Audience :: Developers
Classifier: Programming Language :: Python :: 3
Classifier: Programming Language :: Python :: 3.8
Classifier: Programming Language :: Python :: 3.9
Classifier: Programming Language :: Python :: 3.10
Classifier: Programming Language :: Python :: 3.11
Classifier: Programming Language :: Python :: 3.12
Classifier: Programming Language :: Python :: 3.13
Classifier: Topic :: Software Development :: Quality Assurance
Classifier: Topic :: Software Development :: Testing
Requires-Python: >=3.8
License-File: LICENSE
Requires-Dist: mcp>=0.9.0
Requires-Dist: pylint>=3.0.0
Requires-Dist: flake8>=7.0.0
Requires-Dist: mypy>=1.7.0
Requires-Dist: bandit>=1.7.5
Requires-Dist: radon>=6.0.1
Requires-Dist: autopep8>=2.0.4
Requires-Dist: black>=23.12.0
Requires-Dist: pytest>=7.4.3
Requires-Dist: pytest-cov>=4.1.0
Requires-Dist: pytest-timeout>=2.2.0
Requires-Dist: aiofiles>=23.2.1
Requires-Dist: pydantic>=2.5.0
Provides-Extra: dev
Requires-Dist: pytest>=7.4.3; extra == "dev"
Requires-Dist: pytest-cov>=4.1.0; extra == "dev"
Requires-Dist: pytest-asyncio>=0.21.0; extra == "dev"
Requires-Dist: black>=23.12.0; extra == "dev"
Requires-Dist: mypy>=1.7.0; extra == "dev"
Requires-Dist: pylint>=3.0.0; extra == "dev"
Dynamic: license-file
